sentry_dingding/__init__.py
sentry_dingding/forms.py
sentry_dingding/plugin.py
sentry_dingding_wb-1.1.7.dist-info/METADATA
sentry_dingding_wb-1.1.7.dist-info/WHEEL
sentry_dingding_wb-1.1.7.dist-info/entry_points.txt
sentry_dingding_wb-1.1.7.dist-info/top_level.txt
sentry_dingding_wb-1.1.7.dist-info/RECORD
