Metadata-Version: 2.1
Name: sentry-dingding-wb
Version: 1.1.7
Summary: A Sentry extension which send errors stats to DingDing
Home-page: https://github.com/dreamerldq/sentry-dingding-format
Author: dreamerldq
Author-email: 845790692@qq.com
License: MIT
Keywords: sentry dingding
Platform: UNKNOWN
Classifier: Programming Language :: Python :: 2.7
Classifier: License :: OSI Approved :: MIT License
Requires-Dist: sentry (>=9.0.0)
Requires-Dist: requests
